jpl_small_bodies_de441_n16/__init__.py
jpl_small_bodies_de441_n16/fetch.py
jpl_small_bodies_de441_n16/sb441-n16.bsp
jpl_small_bodies_de441_n16/sb441-n16.md5
jpl_small_bodies_de441_n16/tests/__init__.py
jpl_small_bodies_de441_n16/tests/test_jpl_small_bodies_de441_n16.py
jpl_small_bodies_de441_n16-2021.3.31.1.dist-info/licenses/LICENSE
jpl_small_bodies_de441_n16-2021.3.31.1.dist-info/METADATA
jpl_small_bodies_de441_n16-2021.3.31.1.dist-info/WHEEL
jpl_small_bodies_de441_n16-2021.3.31.1.dist-info/top_level.txt
jpl_small_bodies_de441_n16-2021.3.31.1.dist-info/RECORD
