Metadata-Version: 2.4
Name: jpl_small_bodies_de441_n16
Version: 2021.3.31.1
Summary: JPL Small Bodies DE441 of 16 most massive asteroids.
Author-email: B612 Asteroid Institute <info@b612foundation.org>
License: MIT License
Requires-Python: >=3.7
License-File: LICENSE
Provides-Extra: tests
Requires-Dist: pytest; extra == "tests"
Requires-Dist: spiceypy; extra == "tests"
Dynamic: license-file
